{"data":[{"word":"Lambert Kendal - The Walking Dead","group_id":"569267535516506638"},{"word":"Megan Fox Tongue Smile","group_id":"4017511349271683884","word_type":"2"},{"word":"IPhone 17","group_id":"7093445179720345607","word_type":"2"},{"word":"8000 Tax Refund Updates","group_id":"5238282613437132095","word_type":"2"},{"word":"TikTok Dance In 2025","group_id":"3831200995440054566"},{"word":"Best New Pub Player","group_id":"2897977901797405695"},{"word":"Good Trouble Best Scenes","group_id":"7598045404699630728"},{"word":"Baylor Rush","group_id":"5994922104554535277"},{"word":"Juan Soto Gifts SUV To Baty","group_id":"2616751976868734032"},{"word":"What Happens On February 26","group_id":"1812636819052713951"}],"status_code":0,"status_msg":"","log_id":"202502241220185F87B256D031D3005523"}