{"data":[{"word":"The Walking Dead Clips","group_id":"1891473476478290042"},{"word":"Trending Dance 2025","group_id":"122143697387906367","word_type":"2"},{"word":"Casey Anthony 2025","group_id":"2203362289823848741","word_type":"2"},{"word":"Pope Francis Thanks Supporters","group_id":"7849821692428419802","word_type":"2"},{"word":"Staind - So Far Away","group_id":"9049379251497225265"},{"word":"2025 Women Work Outfits Ideas","group_id":"9043213967453767789"},{"word":"Passion Manhwa Chapter 112 Scenes","group_id":"6035853746166214895"},{"word":"Amish Girls On Tiktok","group_id":"5275700726873374928"},{"word":"505 Girl Trend","group_id":"5671962987911494720"},{"word":"The Subway Girl","group_id":"8470579127556007680"}],"status_code":0,"status_msg":"","log_id":"20250307021805CACFB4E19A4D6128BFE7"}