{"data":[{"word":"Lambert Kendal - The Walking Dead","group_id":"569267535516506638"},{"word":"Megan Fox Tongue Smile","group_id":"4017511349271683884","word_type":"2"},{"word":"TikTok Dance In 2025","group_id":"3831200995440054566","word_type":"2"},{"word":"Get Jiggy Dance Trend","group_id":"5938752944783881814","word_type":"2"},{"word":"Cheating Is A Choice Photo","group_id":"3351774714111460656"},{"word":"Doge Stimulus Check","group_id":"3017422294018996411"},{"word":"Aot Edits","group_id":"4950365047275737669"},{"word":"Ash Trevino Realizing She Got Pranked","group_id":"2181476019625688481"},{"word":"Jason Kelce Reacts To Travis Likely Retiring","group_id":"555176493609809715"},{"word":"Afghanistan Excels In ICC Champions Trophy","group_id":"6173649223900212660"}],"status_code":0,"status_msg":"","log_id":"202502221216538566A7E4C8D8D243E0F0"}