{"data":[{"word":"The Walking Dead Carl Grimes Edits","group_id":"1655936361141133082"},{"word":"Why Is Duo Being Replaced","group_id":"8044003309676557243","word_type":"2"},{"word":"Valentine's Day CapCut Template","group_id":"2205641005737070932","word_type":"2"},{"word":"Kai Moving Out","group_id":"241297732264728426","word_type":"2"},{"word":"I'll Be Your Best Friend And You'll Be Mine","group_id":"4756149644279495361"},{"word":"Best Wi Wi Wi Cat Dance Reactions","group_id":"1128206778095138080"},{"word":"Gta 6 Trailer 2","group_id":"3498408032008225408"},{"word":"TikTok Mashup 2025","group_id":"6378557058380856008"},{"word":"How To Use Hay Day Valentine Design","group_id":"8612380548052198271"},{"word":"Jungwon's Cover Behind The Scenes","group_id":"2475121434835062618"}],"status_code":0,"status_msg":"","log_id":"2025021721091700751AE68B600D182786"}